[{"container-title":"Journal of Guidance, Control, and Dynamics","author":[{"given":"Sébastien","family":"Henry"},{"given":"John A.","family":"Christian"}],"DOI":"10.2514/1.g006989","type":"article-journal","id":"Henry_2023","citation-key":"Henry_2023","ISSN":"1533-3884","issue":"1","issued":{"date-parts":[[2023,1]]},"page":"21-46","publisher":["American Institute of Aeronautics","Astronautics (AIAA)"],"title":"Absolute Triangulation Algorithms for Space Exploration","URL":"http://dx.doi.org/10.2514/1.G006989","volume":"46","_graph":[{"type":"@biblatex/text","data":" @article{Henry_2023, title={Absolute Triangulation Algorithms for Space Exploration}, volume={46}, ISSN={1533-3884}, url={http://dx.doi.org/10.2514/1.G006989}, DOI={10.2514/1.g006989}, number={1}, journal={Journal of Guidance, Control, and Dynamics}, publisher={American Institute of Aeronautics and Astronautics (AIAA)}, author={Henry, Sébastien and Christian, John A.}, year={2023}, month=jan, pages={21–46} }\n"},{"type":"@biblatex/entries+list"},{"type":"@csl/list+object"}]}]